psse/__init__.py
psse/helpers.py
psse/searchengine.py
psse-0.0.2.dist-info/METADATA
psse-0.0.2.dist-info/WHEEL
psse-0.0.2.dist-info/top_level.txt
psse-0.0.2.dist-info/RECORD
