Metadata-Version: 2.1
Name: psse
Version: 0.0.2
Summary: PSSE
Home-page: https://github.com/sgonzalezr94/PythonSimpleSearchEngine
Author: Sebastian Gonzalez
Author-email: sebastiang1493@gmail.com
Keywords: python,psse,search engine,inverted matrix
Classifier: Development Status :: 3 - Alpha
Classifier: Intended Audience :: Education
Classifier: Programming Language :: Python :: 3
Classifier: Operating System :: OS Independent
